ALUCtrl/funct.v
/*
* File Name: funct.v
* Function: this file contains 6bit funct code for R-type instructions.
*/

`define FUNCT_SLL  6'h00 // logical shift left
`define FUNCT_SRL  6'h02 // logical shift right
`define FUNCT_SRA  6'h03 // arithmetic shift right
`define FUNCT_JR   6'h08 // jump register, not gonna implement
`define FUNCT_ADD  6'h20 // add
`define FUNCT_ADDU 6'h21 // add unsigned
`define FUNCT_SUB  6'h22 // subtract
`define FUNCT_SUBU 6'h23 // subtract unsigned
`define FUNCT_AND  6'h24 // and
`define FUNCT_OR   6'h25 // or
`define FUNCT_XOR  6'h26 // xor
`define FUNCT_SLT  6'h2A // set to 1 if less than
`define FUNCT_SLTU 6'h2B // set to 1 if less than unsigned

ALU/aluopdef.v
/*
* File Name: aluopdef.v
* Function: this file serves as a macros definition file
*/


`define ADD 4'h0 // add opcode
`define SUB 4'h1 // subtract opcode
`define NEG 4'h2 // 2's complement opcode
`define ADDU 4'h3 // add unsigned
`define SUBU 4'h4 // subtract unsigned
`define AND 4'h5 // and opcode
`define OR 4'h6 // or opcode
`define XOR 4'h7 // xor opcode
`define NOT 4'h8 // 1's complement opcode
`define ASL 4'h9 // arithmetic shift left opcode
`define ASR 4'hA // arithmetic shift right opcode
`define LSL 4'hB // logical shift left opcode
`define LSR 4'hC // logical shift right opcode

ALUCtrl/aluctrl.v
/*
* File Name: aluctrl.v
* Function: this file describes ALU control unit, which takes 3bit ALUOp
* from control unit and 6bit funct field code from instruction if there's
* any, then output 4bit opcode for ALU.
*
* ALUop | meaning
* -----------------
* 000   | add(for load and store and addi instruction)
* 001   | subtract(beq and slti instruction)
* 010   | R-type instruction
* 011   | and(andi instruction)
* 100   | or(ori instruction)
* 101   | addu(adiu instruction)
* 110   | lsl(lui)
*/

`include "../ALU/aluopdef.v"
`include "funct.v"

module aluctrl(input wire [2:0] aluop,
               input wire [5:0] funct,
               output reg [3:0] opcodeforalu);

always @(aluop, funct) begin
    case (aluop)
        3'b000: opcodeforalu = `ADD;
        3'b001: opcodeforalu = `SUB;
        3'b010: begin // R-type instruction
                   case (funct)
                        `FUNCT_SLL: opcodeforalu = `LSL;
                        `FUNCT_SRL: opcodeforalu = `LSR;
                        `FUNCT_SRA: opcodeforalu = `ASR;
                        `FUNCT_ADD: opcodeforalu = `ADD;
                        `FUNCT_ADDU: opcodeforalu = `ADDU;
                        `FUNCT_SUB: opcodeforalu = `SUB;
                        `FUNCT_SUBU: opcodeforalu = `SUBU;
                        `FUNCT_AND: opcodeforalu = `AND;
                        `FUNCT_OR: opcodeforalu = `OR;
                        `FUNCT_XOR: opcodeforalu = `XOR;
                        `FUNCT_SLT: opcodeforalu = `SUB;
                        `FUNCT_SLTU: opcodeforalu = `SUBU;
                        default: opcodeforalu = 'hx;
                   endcase
                end
        3'b011: opcodeforalu = `AND;
        3'b100: opcodeforalu = `OR;
        3'b101: opcodeforalu = `ADDU;
        3'b110: opcodeforalu = `LSL;
        default: opcodeforalu = 'bx;
    endcase
end

endmodule

ALUCtrl/aluctrl_tb.v
/*
* File Name: aluctrl_tb.v
* Function: this is a testbench file for ALU control module
*/

module aluctrl_tb();
reg [2:0] aluop;
reg [5:0] funct;
wire [3:0] opcodeforalu;

initial begin
    $dumpfile("aluctrl.vcd");
    $dumpvars;
    aluop = 0;
    funct = 'hx;
    $display("aluop\t   funct\t     opcode\t\n");
    $monitor("%b\t      %h\t        %h\t", aluop, funct, opcodeforalu);

    #1 aluop = 0; // add
    #4 aluop = 1; // subtract
    #4 funct = 6'h2A;
    #4 aluop = 3; // and
    #4 aluop = 4; // or
    #4 aluop = 5; // add unsigned

    // R-type test
    #4 aluop = 2;
    #4 funct = 0; // LSL
    #4 funct = 2; // LSR
    #4 funct = 3; // ASR
    #4 funct = 6'h20; // add
    #4 funct = 6'h21; // add unsigned
    #4 funct = 6'h22; // subtract
    #4 funct = 6'h23; // subtract unsigned
    #4 funct = 6'h24; // and
    #4 funct = 6'h25; // or
    #4 funct = 6'h26; // xor
    #4 funct = 6'h2A; // subtract
    #4 funct = 6'h2B; // subtract unsigned
    #4 $finish;
end

// DUT, device under test
aluctrl dut(aluop, funct, opcodeforalu);

endmodule

ALUCtrl/aluctrl.vcd
$date
	Sun Sep 26 10:46:25 2021
$end
$version
	Icarus Verilog
$end
$timescale
	1s
$end
$scope module aluctrl_tb $end
$var wire 4 ! opcodeforalu [3:0] $end
$var reg 3 " aluop [2:0] $end
$var reg 6 # funct [5:0] $end
$scope module dut $end
$var wire 3 $ aluop [2:0] $end
$var wire 6 % funct [5:0] $end
$var reg 4 & opcodeforalu [3:0] $end
$upscope $end
$upscope $end
$enddefinitions $end
#0
$dumpvars
b0 &
bx %
b0 $
bx #
b0 "
b0 !
$end
#5
b1 !
b1 &
b1 "
b1 $
#9
b101010 #
b101010 %
#13
b101 !
b101 &
b11 "
b11 $
#17
b110 !
b110 &
b100 "
b100 $
#21
b11 !
b11 &
b101 "
b101 $
#25
b1 !
b1 &
b10 "
b10 $
#29
b1011 !
b1011 &
b0 #
b0 %
#33
b1100 !
b1100 &
b10 #
b10 %
#37
b1010 !
b1010 &
b11 #
b11 %
#41
b0 !
b0 &
b100000 #
b100000 %
#45
b11 !
b11 &
b100001 #
b100001 %
#49
b1 !
b1 &
b100010 #
b100010 %
#53
b100 !
b100 &
b100011 #
b100011 %
#57
b101 !
b101 &
b100100 #
b100100 %
#61
b110 !
b110 &
b100101 #
b100101 %
#65
b111 !
b111 &
b100110 #
b100110 %
#69
b1 !
b1 &
b101010 #
b101010 %
#73
b100 !
b100 &
b101011 #
b101011 %
