SRAM/sram.v
/*
* File Name: sram.v
* Function: this is module for SRAM (static RAM), the data width and depth is
* parameteraized, it has din for data input, dout for data output,
* cs for chip select, wr for write signal, rd for read signal. To be able to
* use the chip, cs should be set at first, then set either wr or rd pin to
* issue memory operations. The default SRAM has 10K x 32bit memory, with 
* 32bit long address.
*/

module sram (clk, address, din, dout, rd, wr, cs);
parameter AWIDTH = 32;
parameter DWIDTH = 32;
parameter DEPTH = 10240;

input wire clk;
input wire [AWIDTH-1:0] address;
input wire [DWIDTH-1:0] din;
input wire rd;
input wire wr;
input wire cs;
output reg [DWIDTH-1:0] dout;

// internal variable
// the reason to use a temporary dout is to capture any change that may
// affect data output
wire [DWIDTH-1:0] dtempout;

// memory
reg [DWIDTH-1:0] mem[0:DEPTH-1];

assign dtempout = (cs && rd)? mem[address/4]:'hz;

always @(dtempout) begin
    dout = dtempout;
end

always @(posedge clk) begin
    if (cs && wr) mem[address/4] <= din;
end

endmodule

SRAM/sram_tb.v
/*
* File Name: sram_tb.v
* Function: this is a testbench file for SRAM module, the file will test
* both read and write functions, then it will test its chip select pin and 
* test what will happen when read and write happens simultaneously.
*/

module sram_tb();
parameter AWIDTH = 8;
parameter DWIDTH = 32;
parameter DEPTH = 64;

reg clk, rd, wr, cs;
reg [AWIDTH-1:0] addr;
reg [DWIDTH-1:0] din;
wire [DWIDTH-1:0] dout;

initial begin
    clk = 0;
    rd = 0;
    cs = 0;
    wr = 0;
    din = 0;
end

always
    #2 clk = ~clk;

initial begin
    $dumpfile("sram.vcd");
    $dumpvars;
    #1 cs = 1;
    // write
    #1 addr = 8'h5C; // 24th word
    #1 din = 32'h5800FEA9;
    #8 wr = 1;
    #4 wr = 0;
    #1 din = 0;

    // read
    #3 rd = 1;
    #8 rd = 0;

    // write and read happens simultaneously
    #1 din = 32'h86AC57B3;
    #1 addr = 8'hFC; // 63th word 
    #1 rd = 1;
    #1 wr = 1;
    #8 $finish;
end

// DUT, device under test
sram #(.DWIDTH(DWIDTH), .AWIDTH(AWIDTH), .DEPTH(DEPTH)) dut (
                .clk(clk), 
                .rd(rd), 
                .wr(wr),
                .cs(cs),
                .address(addr),
                .din(din),
                .dout(dout));
endmodule

SRAM/sram.vcd
$date
	Fri Sep 24 11:13:54 2021
$end
$version
	Icarus Verilog
$end
$timescale
	1s
$end
$scope module sram_tb $end
$var wire 32 ! dout [31:0] $end
$var reg 8 " addr [7:0] $end
$var reg 1 # clk $end
$var reg 1 $ cs $end
$var reg 32 % din [31:0] $end
$var reg 1 & rd $end
$var reg 1 ' wr $end
$scope module dut $end
$var wire 8 ( address [7:0] $end
$var wire 1 # clk $end
$var wire 1 $ cs $end
$var wire 32 ) din [31:0] $end
$var wire 1 & rd $end
$var wire 1 ' wr $end
$var wire 32 * dtempout [31:0] $end
$var reg 32 + dout [31:0] $end
$upscope $end
$upscope $end
$enddefinitions $end
#0
$dumpvars
bz +
bz *
b0 )
bx (
0'
0&
b0 %
0$
0#
bx "
bz !
$end
#1
1$
#2
b1011100 "
b1011100 (
1#
#3
b1011000000000001111111010101001 %
b1011000000000001111111010101001 )
#4
0#
#6
1#
#8
0#
#10
1#
#11
1'
#12
0#
#14
1#
#15
0'
#16
b0 %
b0 )
0#
#18
1#
#19
b1011000000000001111111010101001 !
b1011000000000001111111010101001 +
b1011000000000001111111010101001 *
1&
#20
0#
#22
1#
#24
0#
#26
1#
#27
bz !
bz +
bz *
0&
#28
b10000110101011000101011110110011 %
b10000110101011000101011110110011 )
0#
#29
b11111100 "
b11111100 (
#30
bx !
bx +
bx *
1&
1#
#31
1'
#32
0#
#34
b10000110101011000101011110110011 !
b10000110101011000101011110110011 +
b10000110101011000101011110110011 *
1#
