RegFile/regfile.v
/*
* File Name: regfile.v
* Function: this is a register file, which contains 32 registers in total,
* the registers' name and their indecies will be identical to the
* implementaion of MIPS architecture.
*/

module regfile #(parameter DWIDTH = 32)( // DWIDTH defines the data width
input wire [4:0] rdaddr1, // read register1 address
input wire [4:0] rdaddr2, // read register2 address
input wire [4:0] wraddr, // write register address
input wire [DWIDTH-1:0] din, // data that written into register
input wire wr, // write to register signal, active HIGH
input wire clk, // clock signal
output reg [DWIDTH-1:0] dout1, // register1 data output
output reg [DWIDTH-1:0] dout2); // register2 data output

// allocate 32 registers
reg [DWIDTH-1:0] register [0:31];

// internal output variable to let register file can write and read the same
// register
wire [DWIDTH-1:0] dtempout1;
wire [DWIDTH-1:0] dtempout2;

always @(dtempout1) begin
    dout1 = dtempout1;
end

always @(dtempout2) begin
    dout2 = dtempout2;
end

// read registers
// zero register always stores value of 0
assign dtempout1 = (rdaddr1 == 0) ? 0:register[rdaddr1];
assign dtempout2 = (rdaddr2 == 0)? 0:register[rdaddr2];

// write data into register
always @(posedge clk) begin
    if (wr) register[wraddr] = din;
end

endmodule

RegFile/regfile_tb.v
/*
* File Name: regfile_tb.v
* Function: this is a testbench for module regfile, the testbench tests 
* the read and write functions, and lastly will test the special case where
* write and read operation happen on the same register simultnaneously.
*/

module regfile_tb();
parameter DWIDTH = 32;

reg [4:0] rdaddr1;
reg [4:0] rdaddr2;
reg [4:0] wraddr;
reg [DWIDTH-1:0] din;
reg clk, wr;
wire [DWIDTH-1:0] dout1;
wire [DWIDTH-1:0] dout2;

initial begin
    clk = 0;
    wr = 0;
    rdaddr1 = 0;
    rdaddr2 = 0;
    din = 0;
end

// supply clock signal
always
   #2 clk = ~clk;

initial begin
    $dumpfile("regfile.vcd");
    $dumpvars;
    $display("time\t readReg1\t readReg2\t writeReg\t writeData\t wr\t Regout1\t Regout2\t\n");
    $monitor("%g\t %d\t %d\t %d\t", $time, rdaddr1, rdaddr2, wraddr,
            "%h\t %b\t %h\t %h\t\n", din, wr, dout1, dout2);
    // write to 6th register, aka $a1
    #4 wraddr = 5;
    #1 din = 32'h192489AC;
    #1 wr = 1;
    #5 wr = 0;

    // write to 15th register, aka $t6
    #1 wraddr = 14;
    #1 din = 32'h70CA7800;
    #1 wr = 1;
    #5 wr = 0;

    // read registers
    #2 rdaddr1 = 14;
    #4 rdaddr2 = 5;

    // test special case where read and write operations on a same register
    // happen simultnaneously
    #1 wraddr = 5;
    #1 din = 32'h658921D3;
    #4 wr = 1;
    #4 wr = 0;

    #4 $finish;
end

// DUT, device under test
regfile #(.DWIDTH(DWIDTH)) dut (
        .rdaddr1(rdaddr1),
        .rdaddr2(rdaddr2),
        .wraddr(wraddr),
        .wr(wr),
        .clk(clk),
        .din(din),
        .dout1(dout1),
        .dout2(dout2));

endmodule

RegFile/regfile.vcd
$date
	Fri Sep 24 16:08:45 2021
$end
$version
	Icarus Verilog
$end
$timescale
	1s
$end
$scope module regfile_tb $end
$var wire 32 ! dout2 [31:0] $end
$var wire 32 " dout1 [31:0] $end
$var reg 1 # clk $end
$var reg 32 $ din [31:0] $end
$var reg 5 % rdaddr1 [4:0] $end
$var reg 5 & rdaddr2 [4:0] $end
$var reg 1 ' wr $end
$var reg 5 ( wraddr [4:0] $end
$scope module dut $end
$var wire 1 # clk $end
$var wire 32 ) din [31:0] $end
$var wire 32 * dtempout1 [31:0] $end
$var wire 32 + dtempout2 [31:0] $end
$var wire 5 , rdaddr1 [4:0] $end
$var wire 5 - rdaddr2 [4:0] $end
$var wire 1 ' wr $end
$var wire 5 . wraddr [4:0] $end
$var reg 32 / dout1 [31:0] $end
$var reg 32 0 dout2 [31:0] $end
$upscope $end
$upscope $end
$enddefinitions $end
#0
$dumpvars
bx 0
bx /
bx .
b0 -
b0 ,
bx +
bx *
b0 )
bx (
0'
b0 &
b0 %
b0 $
0#
bx "
bx !
$end
#2
1#
#4
0#
b101 (
b101 .
#5
b11001001001001000100110101100 $
b11001001001001000100110101100 )
#6
1'
1#
#8
0#
#10
1#
#11
0'
#12
b1110 (
b1110 .
0#
#13
b1110000110010100111100000000000 $
b1110000110010100111100000000000 )
#14
1'
1#
#16
0#
#18
1#
#19
0'
#20
0#
#21
b1110000110010100111100000000000 "
b1110000110010100111100000000000 /
b1110000110010100111100000000000 *
b1110 %
b1110 ,
#22
1#
#24
0#
#25
b11001001001001000100110101100 !
b11001001001001000100110101100 0
b11001001001001000100110101100 +
b101 &
b101 -
#26
b101 (
b101 .
1#
#27
b1100101100010010010000111010011 $
b1100101100010010010000111010011 )
#28
0#
#30
1#
#31
1'
#32
0#
#34
b1100101100010010010000111010011 !
b1100101100010010010000111010011 0
b1100101100010010010000111010011 +
1#
#35
0'
