ALU/aluopdef.v
/*
* File Name: aluopdef.v
* Function: this file serves as a macros definition file
*/


`define ADD 4'h0 // add opcode
`define SUB 4'h1 // subtract opcode
`define NEG 4'h2 // 2's complement opcode
`define ADDU 4'h3 // add unsigned
`define SUBU 4'h4 // subtract unsigned
`define AND 4'h5 // and opcode
`define OR 4'h6 // or opcode
`define XOR 4'h7 // xor opcode
`define NOT 4'h8 // 1's complement opcode
`define ASL 4'h9 // arithmetic shift left opcode
`define ASR 4'hA // arithmetic shift right opcode
`define LSL 4'hB // logical shift left opcode
`define LSR 4'hC // logical shift right opcode

ALU/alu.v
/*
* File Name: alu.v
* Function: this is a 32 bit ALU, it can support add, subtract, 2's
* complement, add unsigned, subtract unsigned, and/or/xor/1's complement, 
* arithmetic shift left/right, logical shift left/right, ALU has 3 flags, 
* namely zero, overflow, negative, they are all active high. ALU's opcode
* is defined by macro.
*/

`include "./aluopdef.v"

module alu(
input wire [31:0] A, // operand A
input wire [31:0] B, // operand B
input wire [3:0] op, // opcode for ALU
output reg [31:0] out, // result of ALU
output reg zero, // zero flag to indicate result is zero, active HIGH
output reg overflow, // flag to indicate result is overflow, active HIGH
output reg negative); // flag to indicate result is negative, active HIGH

wire signed [31:0] signedA; // signed operand A
wire signed [31:0] signedB; // signed operand B

// internal variable used to detect negative in unsigned subtraction 
reg [31:0] tempout; 
// internal variable used to detect overflow and negative in signed operations
reg signed [31:0] signedout;

// convert both operands to signed numbers
assign signedA = A;
assign signedB = B;

always @(A, B, op) begin
    out = 0;
    overflow = 0;
    negative = 0;
    case(op) // calculate result and determine flags
        `ADD : begin
                    out = signedA + signedB;
                    signedout = signedA + signedB;
                    if ((signedA >= 0 && signedB >= 0 && signedout < 0) ||
                        (signedA < 0 && signedB < 0 && signedout >= 0)) begin
                       overflow = 1; 
                    end
                    if ((signedA < 0 && signedB < 0) || 
                        ((out >> 31) == 1 && ~(signedA > 0 && signedB > 0)))
                    begin
                        negative = 1;
                    end
                end
        `SUB : begin
                    out = signedA - signedB;
                    signedout = signedA - signedB;
                    if ((signedA >= 0 && signedB < 0 && signedout < 0) || 
                        (signedA < 0 && signedB >= 0 && signedout >= 0)) begin
                        overflow = 1;
                    end
                    if ((signedA < 0 && signedB > 0) ||
                        ((out >> 31) == 1 && ~(signedA > 0 && signedB < 0)))
                    begin
                        negative = 1;
                    end
                end
        `ADDU : {overflow, out} = A + B;
        `SUBU : begin 
                    {overflow, out} = A - B;
                    {negative, tempout}= {1'b0, A} - {1'b0, B}; 
                end
        `NEG : begin
                    out = 0 - signedA;
                    negative = out >> 31;
                    if (signedA < 0 && out < 0) overflow = 1;
                end
        `AND : out = A & B;
        `OR : out = A | B;
        `XOR : out = A ^ B;
        `NOT : out = ~A;
        `ASL : out = A <<< B;
        `ASR : out = A >>> B;
        `LSL : out = A << B;
        `LSR : out = A >> B;
        default : out = 32'bx;
    endcase

    // determine zero flag
    zero = 0;
    if (op!= 4'hD && op != 4'hE && op != 4'hF && out == 4'h0) begin
        zero = 1;
    end else begin
        zero = 0;
    end
end

endmodule

ALU/alu_tb.v
/*
* File Name: alu_tb.v
* Function: this is test bench file for module ALU in alu.v file.
*/

`include "./aluopdef.v"

module alu_tb();
reg [31:0] A;
reg [31:0] B;
reg signed [31:0] signedA;
reg signed [31:0] signedB;
reg [3:0] op;
wire [31:0] out;
wire signed [31:0] signedout;
wire zero, overflow, negative;
wire szero, soverflow, snegative;

// instance for unsigned number test
alu aluU(
    .A  (A),
    .B  (B),
    .op (op),
    .out (out),
    .zero (zero),
    .overflow (overflow),
    .negative (negative));

// instance for signed number test
// the reason to seperate signed and unsigned to test is that the $display
// function will treat signed number as unsigned number regardless of its
// negative sign, so you need to convert result to negative manually, which
// is tedious
alu aluS(
    .A  (signedA),
    .B  (signedB),
    .op (op),
    .out (signedout),
    .zero (szero),
    .overflow (soverflow),
    .negative (snegative));

task add;
input reg signed [31:0] operandA;
input reg signed [31:0] operandB;
begin
    signedA = operandA;
    signedB = operandB;
    op = `ADD;
end
endtask

task subtract;
input reg signed [31:0] operandA;
input reg signed [31:0] operandB;
begin
    signedA = operandA;
    signedB = operandB;
    op = `SUB;
end
endtask

task negation;
input reg signed [31:0] operandA;
begin
    signedA = operandA;
    op = `NEG;
end
endtask

task addu;
input reg [31:0] operandA;
input reg [31:0] operandB;
begin
    A = operandA;
    B = operandB;
    op = `ADDU;
end
endtask

task subtractu;
input reg [31:0] operandA;
input reg [31:0] operandB;
begin
    A = operandA;
    B = operandB;
    op = `SUBU;
end
endtask

task andtask;
input reg [31:0] operandA;
input reg [31:0] operandB;
begin
    A = operandA;
    B = operandB;
    op = `AND;
end
endtask

task ortask;
input reg [31:0] operandA;
input reg [31:0] operandB;
begin
    A = operandA;
    B = operandB;
    op = `OR;
end
endtask

task xortask;
input reg [31:0] operandA;
input reg [31:0] operandB;
begin
    A = operandA;
    B = operandB;
    op = `XOR;
end
endtask

task nottask;
input reg [31:0] operandA;
begin
    A = operandA;
    op = `NOT;
end
endtask

task asl;
input reg [31:0] operandA;
input reg [31:0] operandB;
begin
    A = operandA;
    B = operandB;
    op = `ASL;
end
endtask

task asr;
input reg [31:0] operandA;
input reg [31:0] operandB;
begin
    A = operandA;
    B = operandB;
    op = `ASR;
end
endtask


task lsl;
input reg [31:0] operandA;
input reg [31:0] operandB;
begin
    A = operandA;
    B = operandB;
    op = `LSL;
end
endtask

task lsr;
input reg [31:0] operandA;
input reg [31:0] operandB;
begin
    A = operandA;
    B = operandB;
    op = `LSR;
end
endtask

initial begin
    $dumpfile("alu.vcd");
    $dumpvars;
end


initial begin
    $display("===========normal test cases==========");
    $display("time\t op\t A\t B\t out\t zero\t overflow\t negative\t signedA\t signedB\t signedout\t szero\t soverflow\t snegative\t\n");
    $monitor("%g\t %h\t %d\t %d\t %d\t %b\t %b\t %b\t %d\t %d\t %d\t %b\t %b\t %b\t\n", 
            $time, op, A, B, out, zero, overflow, negative, 
            signedA, signedB, signedout, szero, soverflow, snegative);
    #4 addu(48464, 344863132);
    #4 add(2152535, -98421354);
    #4 subtractu(46213, 135); 
    #4 subtract(-4431, -24653);
    #4 negation(13);
    #4 negation(-21);
    #4 negation(0);


    #1 $display("=========bitwise and shift operations test cases==========");
    $display("time\t op\t A\t B\t out\t zero\t overflow\t negative\t\n");
    #4 andtask(8, 24);
    #4 ortask(-24, 23);
    #4 xortask(5, 7);
    #4 nottask(124);
    #4 nottask(-73);
    #4 asl(8'b10011101, 2);
    #4 asr(8'b10011101, 2);
    #4 lsl(8'b10011101, 2);
    #4 lsr(8'b10011101, 2);


    $display("===========zero flag test cases==========");
    $display("time\t op\t A\t B\t out\t zero\t overflow\t negative\t\n");
    #4 add(23, -23);
    #4 subtract(0 ,0);
    #4 andtask(4'b1001, 4'b0110);


    $display("===========overflow test cases==========");
    $display("time\t op\t A\t B\t out\t zero\t overflow\t negative\t\n");
    #4 addu(4081813515,548256422);
    #4 add(-1710002356, -2023002144);
    #4 subtract(1600000000, -1052315422);
    #4 subtractu(825361200, 1246482356);

    #4 $finish;
end

endmodule

ALU/alu.vcd
$date
	Thu Sep 23 10:37:54 2021
$end
$version
	Icarus Verilog
$end
$timescale
	1s
$end
$scope module alu_tb $end
$var wire 1 ! zero $end
$var wire 1 " szero $end
$var wire 1 # soverflow $end
$var wire 1 $ snegative $end
$var wire 32 % signedout [31:0] $end
$var wire 1 & overflow $end
$var wire 32 ' out [31:0] $end
$var wire 1 ( negative $end
$var reg 32 ) A [31:0] $end
$var reg 32 * B [31:0] $end
$var reg 4 + op [3:0] $end
$var reg 32 , signedA [31:0] $end
$var reg 32 - signedB [31:0] $end
$scope module aluS $end
$var wire 32 . A [31:0] $end
$var wire 32 / B [31:0] $end
$var wire 4 0 op [3:0] $end
$var wire 32 1 signedA [31:0] $end
$var wire 32 2 signedB [31:0] $end
$var reg 1 $ negative $end
$var reg 32 3 out [31:0] $end
$var reg 1 # overflow $end
$var reg 32 4 signedout [31:0] $end
$var reg 32 5 tempout [31:0] $end
$var reg 1 " zero $end
$upscope $end
$scope module aluU $end
$var wire 32 6 A [31:0] $end
$var wire 32 7 B [31:0] $end
$var wire 4 8 op [3:0] $end
$var wire 32 9 signedA [31:0] $end
$var wire 32 : signedB [31:0] $end
$var reg 1 ( negative $end
$var reg 32 ; out [31:0] $end
$var reg 1 & overflow $end
$var reg 32 < signedout [31:0] $end
$var reg 32 = tempout [31:0] $end
$var reg 1 ! zero $end
$upscope $end
$scope task add $end
$var reg 32 > operandA [31:0] $end
$var reg 32 ? operandB [31:0] $end
$upscope $end
$scope task addu $end
$var reg 32 @ operandA [31:0] $end
$var reg 32 A operandB [31:0] $end
$upscope $end
$scope task andtask $end
$var reg 32 B operandA [31:0] $end
$var reg 32 C operandB [31:0] $end
$upscope $end
$scope task asl $end
$var reg 32 D operandA [31:0] $end
$var reg 32 E operandB [31:0] $end
$upscope $end
$scope task asr $end
$var reg 32 F operandA [31:0] $end
$var reg 32 G operandB [31:0] $end
$upscope $end
$scope task lsl $end
$var reg 32 H operandA [31:0] $end
$var reg 32 I operandB [31:0] $end
$upscope $end
$scope task lsr $end
$var reg 32 J operandA [31:0] $end
$var reg 32 K operandB [31:0] $end
$upscope $end
$scope task negation $end
$var reg 32 L operandA [31:0] $end
$upscope $end
$scope task nottask $end
$var reg 32 M operandA [31:0] $end
$upscope $end
$scope task ortask $end
$var reg 32 N operandA [31:0] $end
$var reg 32 O operandB [31:0] $end
$upscope $end
$scope task subtract $end
$var reg 32 P operandA [31:0] $end
$var reg 32 Q operandB [31:0] $end
$upscope $end
$scope task subtractu $end
$var reg 32 R operandA [31:0] $end
$var reg 32 S operandB [31:0] $end
$upscope $end
$scope task xortask $end
$var reg 32 T operandA [31:0] $end
$var reg 32 U operandB [31:0] $end
$upscope $end
$upscope $end
$enddefinitions $end
#0
$dumpvars
bx U
bx T
bx S
bx R
bx Q
bx P
bx O
bx N
bx M
bx L
bx K
bx J
bx I
bx H
bx G
bx F
bx E
bx D
bx C
bx B
bx A
bx @
bx ?
bx >
bx =
bx <
bx ;
bx :
bx 9
bx 8
bx 7
bx 6
bx 5
bx 4
bx 3
bx 2
bx 1
bx 0
bx /
bx .
bx -
bx ,
bx +
bx *
bx )
x(
bx '
x&
bx %
x$
x#
x"
x!
$end
#4
0"
0$
x#
bx %
bx 3
0!
0(
0&
b10100100011101110111011101100 '
b10100100011101110111011101100 ;
b11 +
b11 0
b11 8
b10100100011100011000110011100 :
b10100100011100011000110011100 *
b10100100011100011000110011100 7
b1011110101010000 9
b1011110101010000 )
b1011110101010000 6
b10100100011100011000110011100 A
b1011110101010000 @
#8
b10100100011101110111011101100 <
b10100100011101110111011101100 '
b10100100011101110111011101100 ;
1$
b11111010010000110000110111101101 4
0#
b11111010010000110000110111101101 %
b11111010010000110000110111101101 3
b0 +
b0 0
b0 8
b11111010001000100011010110010110 2
b11111010001000100011010110010110 -
b11111010001000100011010110010110 /
b1000001101100001010111 1
b1000001101100001010111 ,
b1000001101100001010111 .
b11111010001000100011010110010110 ?
b1000001101100001010111 >
#12
b101111111101010001011000001 5
1#
1$
b101111111101010001011000001 %
b101111111101010001011000001 3
b1011001111111110 =
b1011001111111110 '
b1011001111111110 ;
b100 +
b100 0
b100 8
b10000111 :
b10000111 *
b10000111 7
b1011010010000101 9
b1011010010000101 )
b1011010010000101 6
b10000111 S
b1011010010000101 R
#16
b1011001111111110 <
b1011001111111110 '
b1011001111111110 ;
b100111011111110 4
0$
0#
b100111011111110 %
b100111011111110 3
b1 +
b1 0
b1 8
b11111111111111111001111110110011 2
b11111111111111111001111110110011 -
b11111111111111111001111110110011 /
b11111111111111111110111010110001 1
b11111111111111111110111010110001 ,
b11111111111111111110111010110001 .
b11111111111111111001111110110011 Q
b11111111111111111110111010110001 P
#20
1(
b11111111111111110100101101111011 '
b11111111111111110100101101111011 ;
1$
b11111111111111111111111111110011 %
b11111111111111111111111111110011 3
b10 +
b10 0
b10 8
b1101 1
b1101 ,
b1101 .
b1101 L
#24
0$
b10101 %
b10101 3
b11111111111111111111111111101011 1
b11111111111111111111111111101011 ,
b11111111111111111111111111101011 .
b11111111111111111111111111101011 L
#28
1"
b0 %
b0 3
b0 1
b0 ,
b0 .
b0 L
#33
1"
0(
b1000 '
b1000 ;
b101 +
b101 0
b101 8
b11000 :
b11000 *
b11000 7
b1000 9
b1000 )
b1000 6
b11000 C
b1000 B
#37
0"
b11111111111111111001111110110011 %
b11111111111111111001111110110011 3
b11111111111111111111111111111111 '
b11111111111111111111111111111111 ;
b110 +
b110 0
b110 8
b10111 :
b10111 *
b10111 7
b11111111111111111111111111101000 9
b11111111111111111111111111101000 )
b11111111111111111111111111101000 6
b10111 O
b11111111111111111111111111101000 N
#41
b11111111111111111001111110110011 %
b11111111111111111001111110110011 3
b10 '
b10 ;
b111 +
b111 0
b111 8
b111 :
b111 *
b111 7
b101 9
b101 )
b101 6
b111 U
b101 T
#45
b11111111111111111111111111111111 %
b11111111111111111111111111111111 3
b11111111111111111111111110000011 '
b11111111111111111111111110000011 ;
b1000 +
b1000 0
b1000 8
b1111100 9
b1111100 )
b1111100 6
b1111100 M
#49
b1001000 '
b1001000 ;
b11111111111111111111111110110111 9
b11111111111111111111111110110111 )
b11111111111111111111111110110111 6
b11111111111111111111111110110111 M
#53
1"
b0 %
b0 3
b1001110100 '
b1001110100 ;
b1001 +
b1001 0
b1001 8
b10 :
b10 *
b10 7
b10011101 9
b10011101 )
b10011101 6
b10 E
b10011101 D
#57
1"
b100111 '
b100111 ;
b1010 +
b1010 0
b1010 8
b10 G
b10011101 F
#61
1"
b1001110100 '
b1001110100 ;
b1011 +
b1011 0
b1011 8
b10 I
b10011101 H
#65
1"
b100111 '
b100111 ;
b1100 +
b1100 0
b1100 8
b10 K
b10011101 J
#69
b10011111 <
b10011111 '
b10011111 ;
1"
b0 4
b0 +
b0 0
b0 8
b11111111111111111111111111101001 2
b11111111111111111111111111101001 -
b11111111111111111111111111101001 /
b10111 1
b10111 ,
b10111 .
b11111111111111111111111111101001 ?
b10111 >
#73
b10011011 <
b10011011 '
b10011011 ;
1"
b1 +
b1 0
b1 8
b0 2
b0 -
b0 /
b0 1
b0 ,
b0 .
b0 Q
b0 P
#77
1"
1!
b0 '
b0 ;
b101 +
b101 0
b101 8
b110 :
b110 *
b110 7
b1001 9
b1001 )
b1001 6
b110 C
b1001 B
#81
1"
0!
1&
b10011111110010100001010110001 '
b10011111110010100001010110001 ;
b11 +
b11 0
b11 8
b100000101011011011101010100110 :
b100000101011011011101010100110 *
b100000101011011011101010100110 7
b11110011010010111000100000001011 9
b11110011010010111000100000001011 )
b11110011010010111000100000001011 6
b100000101011011011101010100110 A
b11110011010010111000100000001011 @
#85
b10011111110010100001010110001 <
0&
b10011111110010100001010110001 '
b10011111110010100001010110001 ;
0"
1$
1#
b100001011111101101111100101100 4
b100001011111101101111100101100 %
b100001011111101101111100101100 3
b0 +
b0 0
b0 8
b10000111011010110110111111100000 2
b10000111011010110110111111100000 -
b10000111011010110110111111100000 /
b10011010000100110110111101001100 1
b10011010000100110110111101001100 ,
b10011010000100110110111101001100 .
b10000111011010110110111111100000 ?
b10011010000100110110111101001100 >
#89
1(
b11010010100111011100110101100101 <
b11010010100111011100110101100101 '
b11010010100111011100110101100101 ;
b10011110000101110001111100011110 4
0$
1#
b10011110000101110001111100011110 %
b10011110000101110001111100011110 3
b1 +
b1 0
b1 8
b11000001010001101111000011100010 2
b11000001010001101111000011100010 -
b11000001010001101111000011100010 /
b1011111010111100001000000000000 1
b1011111010111100001000000000000 ,
b1011111010111100001000000000000 .
b11000001010001101111000011100010 Q
b1011111010111100001000000000000 P
#93
1$
b10011110000101110001111100011110 5
1#
b10011110000101110001111100011110 %
b10011110000101110001111100011110 3
b11100110111001100011001101111100 =
1&
1(
b11100110111001100011001101111100 '
b11100110111001100011001101111100 ;
b100 +
b100 0
b100 8
b1001010010010111100111110110100 :
b1001010010010111100111110110100 *
b1001010010010111100111110110100 7
b110001001100100000001100110000 9
b110001001100100000001100110000 )
b110001001100100000001100110000 6
b1001010010010111100111110110100 S
b110001001100100000001100110000 R
