BranchCtrl/branchcodedef.v
/*
* File Name: branchcodedef.v
* Function: this file contains only macros for branch control module, macros
* define which code represents which address selection case
*/

`define NOLOAD 2'b00 // no PC address load, in other word, no jump, no branch
`define SELJUMP 2'b01 // choose address from jump instructions
`define SELBRANCH 2'b10 // choose address from branch instructions

BranchCtrl/branchctrl.v
/*
* File Name: branctrl.v
* Function: though the module name only contains branch, it is in fact
* control both branch and jump instructions, given 3 flags from ALU and all 
* branch and jump control signals from control unit, the module will decode
* it into 2bit, then feed it to a MUX to decide whether we should load a new
* address into PC and which address should we load in, the address from
* branch instructions or the one from jump instructions.
*/

`include "./branchcodedef.v"

module branchctrl( input wire zero, // flag from ALU
                   input wire negative, // flag from ALU
                   input wire overflow, // flag from ALU
                   input wire jump, // jump signal from control unit
                   input wire branchbeq,
                   input wire branchbne,
                   input wire branchblez,
                   input wire branchbgtz,
                   output reg [1:0] out); // 3 cases in total, so we need 2 bits to control MUX

always @(*) begin
    out = `NOLOAD;
    if (jump | branchbeq | branchbne | branchblez | branchbgtz) begin
        if (jump) begin
            // jump instructions detected, so we should jump
            out = `SELJUMP;
        end else begin
            // if we are here it means we are about to determine if 
            // branch condition is met or not
            if (branchbeq & zero & ~negative & ~overflow) out = `SELBRANCH;
            if (branchbne & ~zero) out = `SELBRANCH;
            if (branchblez & (zero | negative)) out = `SELBRANCH;
            if (branchbgtz & ~zero & ~negative) out = `SELBRANCH;
        end
    end
end

endmodule

BranchCtrl/branchctrl_tb.v
/*
* File Name: branchctrl_tb.v
* Function: this is a testbench file for branch control module
*/

module branchctrl_tb();
reg zero, negative, overflow, jump, branchbeq, branchbne, branchblez, branchbgtz;
wire [1:0] out;

initial begin
    $dumpfile("branchctrl.vcd");
    $dumpvars;
    zero = 0;
    negative = 0;
    overflow = 0;
    jump = 0;
    branchbeq = 0;
    branchbne = 0;
    branchblez = 0;
    branchbgtz = 0;

    $display("zero\t neg\t over\t jump\t beq\t bne\t blez\t bgtz\t out\t\n");
    $monitor("%b\t %b\t %b\t %b\t %b\t %b\t %b\t %b\t %b\n",
            zero, negative, overflow, jump, branchbeq, branchbne, branchblez,
            branchbgtz, out);
    // test jump
    #4 zero = 1;
    #4 jump = 1;

    // test beq
    #4 jump = 0;
    #4 branchbeq = 1;

    // test bne
    #4 branchbeq = 0;
    #4 branchbne = 1;
    #4 zero = 0;
    #4 overflow = 1;

    // test blez
    #4 branchbne = 0;
    #4 branchblez = 1;
    #4 zero = 1;
    #4 zero = 0;
    #4 negative = 1;

    // test bgtz
    #4 branchblez = 0;
    #4 branchbgtz = 1;
    #4 overflow = 0;
    #4 negative = 0;

    #1 $finish;
end

// DUT, device under test
branchctrl dut(.zero(zero),
                .negative(negative),
                .overflow(overflow),
                .jump(jump),
                .branchbeq(branchbeq),
                .branchbne(branchbne),
                .branchblez(branchblez),
                .branchbgtz(branchbgtz),
                .out(out));
endmodule

BranchCtrl/branchctrl.vcd
$date
	Mon Sep 27 15:38:35 2021
$end
$version
	Icarus Verilog
$end
$timescale
	1s
$end
$scope module branchctrl_tb $end
$var wire 2 ! out [1:0] $end
$var reg 1 " branchbeq $end
$var reg 1 # branchbgtz $end
$var reg 1 $ branchblez $end
$var reg 1 % branchbne $end
$var reg 1 & jump $end
$var reg 1 ' negative $end
$var reg 1 ( overflow $end
$var reg 1 ) zero $end
$scope module dut $end
$var wire 1 " branchbeq $end
$var wire 1 # branchbgtz $end
$var wire 1 $ branchblez $end
$var wire 1 % branchbne $end
$var wire 1 & jump $end
$var wire 1 ' negative $end
$var wire 1 ( overflow $end
$var wire 1 ) zero $end
$var reg 2 * out [1:0] $end
$upscope $end
$upscope $end
$enddefinitions $end
#0
$dumpvars
b0 *
0)
0(
0'
0&
0%
0$
0#
0"
b0 !
$end
#4
1)
#8
b1 !
b1 *
1&
#12
b0 !
b0 *
0&
#16
b10 !
b10 *
1"
#20
b0 !
b0 *
0"
#24
1%
#28
b10 !
b10 *
0)
#32
b10 !
b10 *
1(
#36
b0 !
b0 *
0%
#40
1$
#44
b10 !
b10 *
1)
#48
b0 !
b0 *
0)
#52
b10 !
b10 *
1'
#56
b0 !
b0 *
0$
#60
1#
#64
0(
#68
b10 !
b10 *
0'
